phonetisaurus/__init__.py
phonetisaurus/__main__.py
phonetisaurus/py.typed
phonetisaurus/bin/x86_64/farcompilestrings
phonetisaurus/bin/x86_64/farcreate
phonetisaurus/bin/x86_64/farequal
phonetisaurus/bin/x86_64/farextract
phonetisaurus/bin/x86_64/farinfo
phonetisaurus/bin/x86_64/farisomorphic
phonetisaurus/bin/x86_64/farprintstrings
phonetisaurus/bin/x86_64/fstarcsort
phonetisaurus/bin/x86_64/fstclosure
phonetisaurus/bin/x86_64/fstcompile
phonetisaurus/bin/x86_64/fstcompose
phonetisaurus/bin/x86_64/fstconcat
phonetisaurus/bin/x86_64/fstconnect
phonetisaurus/bin/x86_64/fstconvert
phonetisaurus/bin/x86_64/fstdeterminize
phonetisaurus/bin/x86_64/fstdifference
phonetisaurus/bin/x86_64/fstdisambiguate
phonetisaurus/bin/x86_64/fstdraw
phonetisaurus/bin/x86_64/fstencode
phonetisaurus/bin/x86_64/fstepsnormalize
phonetisaurus/bin/x86_64/fstequal
phonetisaurus/bin/x86_64/fstequivalent
phonetisaurus/bin/x86_64/fstinfo
phonetisaurus/bin/x86_64/fstintersect
phonetisaurus/bin/x86_64/fstinvert
phonetisaurus/bin/x86_64/fstisomorphic
phonetisaurus/bin/x86_64/fstmap
phonetisaurus/bin/x86_64/fstminimize
phonetisaurus/bin/x86_64/fstprint
phonetisaurus/bin/x86_64/fstproject
phonetisaurus/bin/x86_64/fstprune
phonetisaurus/bin/x86_64/fstpush
phonetisaurus/bin/x86_64/fstrandgen
phonetisaurus/bin/x86_64/fstrelabel
phonetisaurus/bin/x86_64/fstreplace
phonetisaurus/bin/x86_64/fstreverse
phonetisaurus/bin/x86_64/fstreweight
phonetisaurus/bin/x86_64/fstrmepsilon
phonetisaurus/bin/x86_64/fstshortestdistance
phonetisaurus/bin/x86_64/fstshortestpath
phonetisaurus/bin/x86_64/fstsymbols
phonetisaurus/bin/x86_64/fstsynchronize
phonetisaurus/bin/x86_64/fsttopsort
phonetisaurus/bin/x86_64/fstunion
phonetisaurus/bin/x86_64/phonetisaurus-align
phonetisaurus/bin/x86_64/phonetisaurus-apply
phonetisaurus/bin/x86_64/phonetisaurus-arpa2wfst
phonetisaurus/bin/x86_64/phonetisaurus-g2pfst
phonetisaurus/bin/x86_64/phonetisaurus-g2prnn
phonetisaurus/bin/x86_64/phonetisaurus-train
phonetisaurus/bin/x86_64/rnnlm
phonetisaurus-0.2.0.dist-info/LICENSE
phonetisaurus-0.2.0.dist-info/METADATA
phonetisaurus-0.2.0.dist-info/WHEEL
phonetisaurus-0.2.0.dist-info/entry_points.txt
phonetisaurus-0.2.0.dist-info/top_level.txt
phonetisaurus-0.2.0.dist-info/RECORD
