Metadata-Version: 2.1
Name: phonetisaurus
Version: 0.2.0
Summary: Python wrapper for phonetisaurus grapheme to phoneme tool
Home-page: https://github.com/rhasspy/phonetisaurus-pypi
Author: Michael Hansen
Author-email: mike@rhasspy.org
License: UNKNOWN
Platform: UNKNOWN
Classifier: Programming Language :: Python :: 3
Classifier: Programming Language :: Python :: 3.7
Classifier: Programming Language :: Python :: 3.8
Classifier: License :: OSI Approved :: MIT License
Requires-Python: >=3.7
